argus_api/__init__.py
argus_api/_validators.py
argus_api/api/__init__.py
argus_api/api/alarms/__init__.py
argus_api/api/alarms/v1/__init__.py
argus_api/api/alarms/v1/alarm.py
argus_api/api/alarms/v1/category.py
argus_api/api/alarms/v1/mitre.py
argus_api/api/alarms/v1/signature.py
argus_api/api/assets/__init__.py
argus_api/api/assets/v2/__init__.py
argus_api/api/assets/v2/asset.py
argus_api/api/assets/v2/component/__init__.py
argus_api/api/assets/v2/component/component_definition.py
argus_api/api/assets/v2/cpe.py
argus_api/api/assets/v2/datasource.py
argus_api/api/assets/v2/group.py
argus_api/api/assets/v2/import_/__init__.py
argus_api/api/assets/v2/import_/import_asset.py
argus_api/api/assets/v2/servicetask.py
argus_api/api/assets/v2/vulnerability.py
argus_api/api/authentication/__init__.py
argus_api/api/authentication/v1/__init__.py
argus_api/api/authentication/v1/apikey.py
argus_api/api/authentication/v1/authorization/__init__.py
argus_api/api/authentication/v1/authorization/authorization_validate.py
argus_api/api/authentication/v1/client.py
argus_api/api/authentication/v1/cloudprovider/__init__.py
argus_api/api/authentication/v1/cloudprovider/cloudprovider_aws.py
argus_api/api/authentication/v1/constrain.py
argus_api/api/authentication/v1/customer/__init__.py
argus_api/api/authentication/v1/customer/customer_events.py
argus_api/api/authentication/v1/enroll.py
argus_api/api/authentication/v1/enrollment.py
argus_api/api/authentication/v1/events.py
argus_api/api/authentication/v1/impersonate.py
argus_api/api/authentication/v1/ldap/__init__.py
argus_api/api/authentication/v1/ldap/ldap_authenticate.py
argus_api/api/authentication/v1/logout.py
argus_api/api/authentication/v1/methods.py
argus_api/api/authentication/v1/oauth/__init__.py
argus_api/api/authentication/v1/oauth/oauth_authorize.py
argus_api/api/authentication/v1/openid/__init__.py
argus_api/api/authentication/v1/openid/openid_authorize.py
argus_api/api/authentication/v1/password.py
argus_api-5.0.0.dist-info/METADATA
argus_api-5.0.0.dist-info/WHEEL
argus_api-5.0.0.dist-info/licenses/LICENSE
argus_api-5.0.0.dist-info/RECORD
