Metadata-Version: 2.4
Name: argus-api
Version: 5.0.0
Summary: SDK for the Argus API
License: ISC
License-File: LICENSE
Author: mnemonic
Author-email: opensource@mnemonic.no
Requires-Python: >=3.9,<4.0
Classifier: License :: OSI Approved
Classifier: Programming Language :: Python :: 3
Classifier: Programming Language :: Python :: 3.9
Classifier: Programming Language :: Python :: 3.10
Classifier: Programming Language :: Python :: 3.11
Classifier: Programming Language :: Python :: 3.12
Classifier: Programming Language :: Python :: 3.13
Classifier: Programming Language :: Python :: 3.14
Provides-Extra: oauth
Requires-Dist: certifi (>=2022.12.7)
Requires-Dist: importlib-resources (>=5.4.0,<6.0.0)
Requires-Dist: importlib_metadata
Requires-Dist: requests (>=2.32.3,<3.0.0)
Requires-Dist: requests-oauthlib (>=1.3.1,<2.0.0) ; extra == "oauth"
Requires-Dist: typing-extensions
Project-URL: Documentation, https://argus-api.docs.mnemonic.no
Project-URL: Homepage, https://mnemonic.io
